cutbucket/__init__.py
cutbucket/cuts.py
cutbucket-0.2.0.dist-info/METADATA
cutbucket-0.2.0.dist-info/RECORD
cutbucket-0.2.0.dist-info/WHEEL
cutbucket-0.2.0.dist-info/top_level.txt
