Metadata-Version: 2.1
Name: cutbucket
Version: 0.2.0
Summary: Tools for sharing and version control of numpy ndarrays between collaborators
Home-page: https://github.com/ucbpylegroup/CutBucket
Author: Caleb Fink
Author-email: cwfink@berkeley.edu
License: UNKNOWN
Platform: UNKNOWN
